Metadata-Version: 2.1
Name: pyloading
Version: 1.0.0
Summary: Loading made easy
Home-page: https://github.com/DevER-M/pyloading
Author: Dever
Author-email: 
License: MIT
Keywords: Loading (console based)
Platform: UNKNOWN
Classifier: Development Status :: 5 - Production/Stable
Classifier: Intended Audience :: Education
Classifier: Operating System :: OS Independent
Classifier: License :: OSI Approved :: MIT License
Classifier: Programming Language :: Python :: 3
